nlcLatex/__init__.py
nlcLatex/base.py
nlcLatex/document.py
nlcLatex/process.py
nlcLatex-0.1.0.dist-info/METADATA
nlcLatex-0.1.0.dist-info/WHEEL
nlcLatex-0.1.0.dist-info/top_level.txt
nlcLatex-0.1.0.dist-info/RECORD
