Metadata-Version: 2.1
Name: nlcLatex
Version: 0.1.0
Summary: Tools for Latex Documents
Home-page: UNKNOWN
Author: Bernhard W. Radermacher
Author-email: bernhard.radermacher@netlink-consulting.com
License: UNKNOWN
Platform: UNKNOWN
Classifier: Programming Language :: Python :: 3
Classifier: License :: OSI Approved :: MIT License
Classifier: Operating System :: OS Independent
Requires-Python: >=3.6
